cachely/__init__.py
cachely/__main__.py
cachely/__version__.py
cachely/client.py
cachely/backends/__init__.py
cachely/backends/base.py
cachely/backends/fs.py
cachely/backends/sqlite.py
cachely-0.2.dist-info/licenses/LICENSE
cachely-0.2.dist-info/METADATA
cachely-0.2.dist-info/WHEEL
cachely-0.2.dist-info/entry_points.txt
cachely-0.2.dist-info/top_level.txt
cachely-0.2.dist-info/RECORD
